[{"resourceType":"ValueSet","id":"2.16.840.1.113762.1.4.1110.50","meta":{"versionId":"8","lastUpdated":"2023-12-21T17:43:03.000-05:00","profile":["http://hl7.org/fhir/StructureDefinition/shareablevalueset","http://hl7.org/fhir/us/cqfmeasures/StructureDefinition/computable-valueset-cqfm","http://hl7.org/fhir/us/cqfmeasures/StructureDefinition/publishable-valueset-cqfm"]},"extension":[{"url":"http://hl7.org/fhir/StructureDefinition/valueset-effectiveDate","valueDate":"2020-03-05"}],"url":"http://cts.nlm.nih.gov/fhir/ValueSet/2.16.840.1.113762.1.4.1110.50","identifier":[{"system":"urn:ietf:rfc:3986","value":"urn:oid:2.16.840.1.113762.1.4.1110.50"}],"version":"20200305","name":"RivaroxabanForVTEProphylaxis","title":"Rivaroxaban for VTE Prophylaxis","status":"retired","experimental":false,"date":"2020-03-05T01:00:20-05:00","publisher":"TJC EH Steward","expansion":{"identifier":"urn:uuid:3f7fb4f8-0891-4d00-b845-8babfde0d756","timestamp":"2024-02-11T11:07:02-05:00","total":7,"offset":0,"parameter":[{"name":"count","valueInteger":1000},{"name":"offset","valueInteger":0}],"contains":[{"system":"http://www.nlm.nih.gov/research/umls/rxnorm","version":"01022024","code":"1114198","display":"rivaroxaban 10 MG Oral Tablet"},{"system":"http://www.nlm.nih.gov/research/umls/rxnorm","version":"01022024","code":"1232082","display":"rivaroxaban 15 MG Oral Tablet"},{"system":"http://www.nlm.nih.gov/research/umls/rxnorm","version":"01022024","code":"1232086","display":"rivaroxaban 20 MG Oral Tablet"},{"system":"http://www.nlm.nih.gov/research/umls/rxnorm","version":"01022024","code":"1549682","display":"{42 (rivaroxaban 15 MG Oral Tablet) / 9 (rivaroxaban 20 MG Oral Tablet) } Pack"},{"system":"http://www.nlm.nih.gov/research/umls/rxnorm","version":"01022024","code":"1927856","display":"betrixaban 40 MG Oral Capsule"},{"system":"http://www.nlm.nih.gov/research/umls/rxnorm","version":"01022024","code":"1927864","display":"betrixaban 80 MG Oral Capsule"},{"system":"http://www.nlm.nih.gov/research/umls/rxnorm","version":"01022024","code":"2059015","display":"rivaroxaban 2.5 MG Oral Tablet"}]}}]
